CrazyFlyt/__init__.py
CrazyFlyt/drone_controller.py
CrazyFlyt/simulator.py
CrazyFlyt/swarm_controller.py
CrazyFlyt/models/cf2x/cf2.dae
CrazyFlyt/models/cf2x/cf2x.urdf
CrazyFlyt/models/cf2x/cf2x.yaml
CrazyFlyt-0.0.5.dist-info/LICENSE.txt
CrazyFlyt-0.0.5.dist-info/METADATA
CrazyFlyt-0.0.5.dist-info/WHEEL
CrazyFlyt-0.0.5.dist-info/top_level.txt
CrazyFlyt-0.0.5.dist-info/RECORD
