Metadata-Version: 2.1
Name: CrazyFlyt
Version: 0.0.5
Summary: Crazyflie UAV simulation based on the PyFlyt library
Author-email: Jet <taijunjet@hotmail.com>
License: MIT License
Project-URL: Repository, https://github.com/jjshoots/CrazyFlyt
Project-URL: Bug Report, https://github.com/jjshoots/CrazyFlyt/issues
Keywords: Crazyflie,UAVs,drones,Quadcopter
Classifier: Programming Language :: Python :: 3
Classifier: License :: OSI Approved :: MIT License
Classifier: Operating System :: OS Independent
Requires-Python: >=3.8
License-File: LICENSE.txt
Requires-Dist: numpy
Requires-Dist: cflib
Requires-Dist: cfclient
Requires-Dist: pyflyt
